tcdt/__init__.py
tcdt/tcdt.py
tcdt-0.1.dist-info/LICENSE
tcdt-0.1.dist-info/METADATA
tcdt-0.1.dist-info/WHEEL
tcdt-0.1.dist-info/top_level.txt
tcdt-0.1.dist-info/RECORD
