Metadata-Version: 2.1
Name: tcdt
Version: 0.1
Summary: Implementation of a Time-Changing Decision Tree classifier
Home-page: https://github.com/evonx/tcdt
Author: 0xCC
License: UNKNOWN
Platform: UNKNOWN
Classifier: Programming Language :: Python :: 3
Classifier: License :: OSI Approved :: MIT License
Classifier: Operating System :: OS Independent
Requires-Python: >=3.6
Requires-Dist: numpy
Requires-Dist: pandas
